jiracli/__init__.py
jiracli/_version.py
jiracli/cache.py
jiracli/cli.py
jiracli/errors.py
jiracli/interface.py
jiracli/processor.py
jiracli/utils.py
jiracli/version.py
jiracli/bridge/__init__.py
jiracli/bridge/rest.py
jiracli/bridge/soap.py
jira_cli-3.0.dist-info/LICENSE.txt
jira_cli-3.0.dist-info/METADATA
jira_cli-3.0.dist-info/WHEEL
jira_cli-3.0.dist-info/entry_points.txt
jira_cli-3.0.dist-info/top_level.txt
jira_cli-3.0.dist-info/RECORD
