Metadata-Version: 2.1
Name: jira-cli
Version: 3.0
Summary: command line utility for interacting with jira
Home-page: http://github.com/alisaifee/jira-cli
Author: Ali-Akber Saifee
Author-email: ali@indydevs.org
License: MIT
Platform: UNKNOWN
Classifier: Development Status :: 5 - Production/Stable
Classifier: Environment :: Console
Classifier: Intended Audience :: Developers
Classifier: Intended Audience :: End Users/Desktop
Classifier: License :: OSI Approved :: MIT License
Classifier: Operating System :: MacOS
Classifier: Operating System :: POSIX :: Linux
Classifier: Operating System :: OS Independent
Classifier: Topic :: Software Development :: Bug Tracking
Classifier: Programming Language :: Python :: 2.7
Requires-Dist: termcolor
Requires-Dist: six
Requires-Dist: ordereddict
Requires-Dist: jira
Requires-Dist: requests
Requires-Dist: argparse
Requires-Dist: suds-jurko
Requires-Dist: keyring
Requires-Dist: keyrings.alt
